celery_fastapi/__init__.py
celery_fastapi/app.py
celery_fastapi/cli.py
celery_fastapi/core.py
celery_fastapi/py.typed
celery_fastapi/server.py
celery_fastapi-0.1.3.dist-info/METADATA
celery_fastapi-0.1.3.dist-info/WHEEL
celery_fastapi-0.1.3.dist-info/entry_points.txt
celery_fastapi-0.1.3.dist-info/licenses/LICENSE
celery_fastapi-0.1.3.dist-info/RECORD
