Metadata-Version: 2.4
Name: celery-fastapi
Version: 0.1.3
Summary: Automatic REST API generation for Celery tasks with FastAPI
License: MIT
License-File: LICENSE
Keywords: celery,fastapi,rest,api,tasks,async,queue
Author: ilkerkara
Author-email: ilkerkara@outlook.com.tr
Requires-Python: >=3.11,<4.0
Classifier: Development Status :: 4 - Beta
Classifier: Environment :: Web Environment
Classifier: Framework :: FastAPI
Classifier: Intended Audience :: Developers
Classifier: License :: OSI Approved :: MIT License
Classifier: Operating System :: OS Independent
Classifier: Programming Language :: Python :: 3
Classifier: Programming Language :: Python :: 3.11
Classifier: Programming Language :: Python :: 3.12
Classifier: Programming Language :: Python :: 3.13
Classifier: Programming Language :: Python :: 3.14
Classifier: Topic :: Internet :: WWW/HTTP :: HTTP Servers
Classifier: Topic :: System :: Distributed Computing
Classifier: Typing :: Typed
Provides-Extra: all
Provides-Extra: cli
Provides-Extra: eventlet
Provides-Extra: gevent
Provides-Extra: gunicorn
Provides-Extra: multipart
Provides-Extra: orjson
Provides-Extra: rabbitmq
Provides-Extra: redis
Provides-Extra: server
Provides-Extra: standard
Provides-Extra: ujson
Provides-Extra: uvicorn
Requires-Dist: celery (>=5.3.0)
Requires-Dist: eventlet (>=0.33.0) ; extra == "eventlet"
Requires-Dist: fastapi (>=0.100.0)
Requires-Dist: gevent (>=23.0.0) ; extra == "gevent"
Requires-Dist: gunicorn (>=21.0.0) ; extra == "gunicorn" or extra == "all"
Requires-Dist: httpx (>=0.27.0) ; extra == "all"
Requires-Dist: kombu (>=5.3.0) ; extra == "rabbitmq" or extra == "all"
Requires-Dist: orjson (>=3.9.0) ; extra == "orjson" or extra == "all"
Requires-Dist: pydantic (>=2.0.0)
Requires-Dist: python-multipart (>=0.0.6) ; extra == "multipart" or extra == "all"
Requires-Dist: redis (>=5.0.0) ; extra == "redis" or extra == "standard" or extra == "all"
Requires-Dist: rich (>=13.0.0) ; extra == "cli" or extra == "standard" or extra == "all"
Requires-Dist: typer (>=0.9.0) ; extra == "cli" or extra == "standard" or extra == "all"
Requires-Dist: ujson (>=5.8.0) ; extra == "ujson"
Requires-Dist: uvicorn[standard] (>=0.23.0) ; extra == "uvicorn" or extra == "gunicorn" or extra == "server" or extra == "cli" or extra == "standard" or extra == "all"
Project-URL: Documentation, https://github.com/karailker/celery-fastapi#readme
Project-URL: Homepage, https://github.com/karailker/celery-fastapi
Project-URL: Repository, https://github.com/karailker/celery-fastapi
